mypackage/__init__.py
mypackage/mypackage.py
package_afraz-0.1.dist-info/LICENSE
package_afraz-0.1.dist-info/METADATA
package_afraz-0.1.dist-info/WHEEL
package_afraz-0.1.dist-info/top_level.txt
package_afraz-0.1.dist-info/RECORD
