Metadata-Version: 2.1
Name: package-afraz
Version: 0.1
Summary: Afraz Ahmed A is a Python developer working with QCoDes. We will launch our package very soon.
Home-page: https://github.com/Afraz/mypackage
Author: Afraz Ahmed A
Author-email: afraz@gmail.com
Classifier: Programming Language :: Python :: 3
Classifier: License :: OSI Approved :: MIT License
Classifier: Operating System :: OS Independent
License-File: LICENSE
